{
    "Ar36": {
        "error": 0.0081764527589758152, 
        "fit": "Parabolic", 
        "value": 0.55626431843877033
    }, 
    "Ar37": {
        "error": 0.12256901357267837, 
        "fit": "linear", 
        "value": 15.61234111129929
    }, 
    "Ar38": {
        "error": 0.10204501554773478, 
        "fit": "linear", 
        "value": 0.23800493493725189
    }, 
    "Ar39": {
        "error": 0.06260653798314933, 
        "fit": "Parabolic", 
        "value": 16.453489516916715
    }, 
    "Ar40": {
        "error": 0.17051152356345878, 
        "fit": "Parabolic", 
        "value": 175.9940021578646
    }, 
    "Ar41": {
        "error": 0.099704052488663528, 
        "fit": "linear", 
        "value": 0.0048610203510510595
    }
}